[{"categories":null,"content":"明天更新","keywords":null,"title":"Silicon Photonics: an Introduction","uri":"http://notes.skyletter.cn/silicon/"},{"categories":null,"content":"","keywords":null,"title":"Sky Note Site","uri":"http://notes.skyletter.cn/"},{"categories":null,"content":"搭建本站的目的在于督促自己学习，区别于原Blog站点，本站主要以简洁明了的方式进行学习记录，一切内容围绕学习和心得。\n","keywords":null,"title":"Plan at 2019.06.02","uri":"http://notes.skyletter.cn/plan1/"},{"categories":null,"content":"","keywords":null,"title":"Archives","uri":"http://notes.skyletter.cn/archives/"},{"categories":null,"content":"","keywords":null,"title":"Categories","uri":"http://notes.skyletter.cn/categories/"},{"categories":null,"content":"","keywords":null,"title":"Search","uri":"http://notes.skyletter.cn/search/"},{"categories":null,"content":"","keywords":null,"title":"Tags","uri":"http://notes.skyletter.cn/tags/"}]